alibabacloud_paillmtrace20240311/__init__.py
alibabacloud_paillmtrace20240311/client.py
alibabacloud_paillmtrace20240311/models.py
alibabacloud_paillmtrace20240311-1.1.4.dist-info/LICENSE
alibabacloud_paillmtrace20240311-1.1.4.dist-info/METADATA
alibabacloud_paillmtrace20240311-1.1.4.dist-info/WHEEL
alibabacloud_paillmtrace20240311-1.1.4.dist-info/top_level.txt
alibabacloud_paillmtrace20240311-1.1.4.dist-info/RECORD
